LICENSE
README.md
setup.py
libname/__init__.py
libname/random_password.py
rand_password_generator_python.egg-info/PKG-INFO
rand_password_generator_python.egg-info/SOURCES.txt
rand_password_generator_python.egg-info/dependency_links.txt
rand_password_generator_python.egg-info/top_level.txt